py_gsuite_apis/__init__.py
py_gsuite_apis/core/__init__.py
py_gsuite_apis/core/config.py
py_gsuite_apis/models/__init__.py
py_gsuite_apis/models/google_apis/__init__.py
py_gsuite_apis/models/google_apis/drive.py
py_gsuite_apis/models/google_apis/sheets/__init__.py
py_gsuite_apis/models/google_apis/sheets/enums.py
py_gsuite_apis/models/google_apis/sheets/other.py
py_gsuite_apis/models/google_apis/sheets/charts/__init__.py
py_gsuite_apis/models/google_apis/sheets/charts/enums.py
py_gsuite_apis/models/google_apis/slides/__init__.py
py_gsuite_apis/models/google_apis/slides/enums.py
py_gsuite_apis/models/google_apis/slides/image.py
py_gsuite_apis/models/google_apis/slides/line.py
py_gsuite_apis/models/google_apis/slides/other.py
py_gsuite_apis/models/google_apis/slides/page.py
py_gsuite_apis/models/google_apis/slides/requests.py
py_gsuite_apis/models/google_apis/slides/shape.py
py_gsuite_apis/models/google_apis/slides/table.py
py_gsuite_apis/models/google_apis/slides/video.py
py_gsuite_apis/services/__init__.py
py_gsuite_apis/services/filesystem.py
py_gsuite_apis/services/google_apis/__init__.py
py_gsuite_apis/services/google_apis/auth.py
py_gsuite_apis/services/google_apis/drive.py
py_gsuite_apis/services/google_apis/slides.py
py_gsuite_apis/services/google_apis/sheets/__init__.py
py_gsuite_apis/services/google_apis/sheets/charts.py
py_gsuite_apis-0.0.8.dist-info/LICENSE
py_gsuite_apis-0.0.8.dist-info/METADATA
py_gsuite_apis-0.0.8.dist-info/WHEEL
py_gsuite_apis-0.0.8.dist-info/top_level.txt
py_gsuite_apis-0.0.8.dist-info/RECORD
