Metadata-Version: 2.1
Name: py-gsuite-apis
Version: 0.0.8
Summary: Standarize and simplify requests to various GSuite APIs
Home-page: https://github.com/jastor11/py-gsuite-apis
Author: Jeff Astor
Author-email: jeff@astor.io
License: UNKNOWN
Platform: UNKNOWN
Classifier: Programming Language :: Python :: 3
Classifier: License :: OSI Approved :: MIT License
Classifier: Operating System :: OS Independent
Requires-Python: >=3.7
Requires-Dist: pydantic[dotenv] (==1.7.3)
Requires-Dist: pandas (==1.2.1)
Requires-Dist: google-api-python-client (==1.12.8)
Requires-Dist: google-auth-oauthlib (==0.4.0)
Requires-Dist: google-auth-httplib2 (==0.0.4)
Requires-Dist: google-auth (==1.24.0)
Requires-Dist: typing-extensions (==3.7.4.3)
